odoo/addons/ssi_transaction_date_due_mixin/README.rst
odoo/addons/ssi_transaction_date_due_mixin/__init__.py
odoo/addons/ssi_transaction_date_due_mixin/__manifest__.py
odoo/addons/ssi_transaction_date_due_mixin/models/__init__.py
odoo/addons/ssi_transaction_date_due_mixin/models/mixin_transaction_date_due.py
odoo/addons/ssi_transaction_date_due_mixin/static/description/icon.png
odoo14_addon_ssi_transaction_date_due_mixin-14.0.1.0.0.dist-info/METADATA
odoo14_addon_ssi_transaction_date_due_mixin-14.0.1.0.0.dist-info/WHEEL
odoo14_addon_ssi_transaction_date_due_mixin-14.0.1.0.0.dist-info/top_level.txt
odoo14_addon_ssi_transaction_date_due_mixin-14.0.1.0.0.dist-info/RECORD
